cornershop/__init__.py
cornershop/cornershop.py
cornershop/models.py
cornershop-0.1.0.dist-info/LICENSE
cornershop-0.1.0.dist-info/METADATA
cornershop-0.1.0.dist-info/WHEEL
cornershop-0.1.0.dist-info/top_level.txt
cornershop-0.1.0.dist-info/RECORD
