Metadata-Version: 2.1
Name: cornershop
Version: 0.1.0
Summary: A Python wrapper for Cornershop by Uber's API.
Home-page: https://github.com/GusFurtado/cornershop
Author: Gustavo Furtado
Author-email: gustavofurtado2@gmail.com
License: MIT
Download-URL: https://github.com/GusFurtado/cornershop/archive/0.1.0.tar.gz
Keywords: python,api,wrapper,uber,delivery,cornershop
Platform: UNKNOWN
Classifier: Development Status :: 3 - Alpha
Classifier: Intended Audience :: Developers
Classifier: Intended Audience :: Other Audience
Classifier: Topic :: Other/Nonlisted Topic
Classifier: License :: OSI Approved :: MIT License
Classifier: Natural Language :: English
Classifier: Programming Language :: Python :: 3
Classifier: Programming Language :: Python :: 3.6
Requires-Dist: requests
